{
  "main": {
    "id": "b3af0e7ed1f0e46d",
    "type": "split",
    "children": [
      {
        "id": "622f6ed1877640a1",
        "type": "tabs",
        "children": [
          {
            "id": "9feaaa701d1f0a9f",
            "type": "leaf",
            "state": {
              "type": "markdown",
              "state": {
                "file": "Untitled 1.md",
                "mode": "preview",
                "source": true
              }
            }
          }
        ]
      }
    ],
    "direction": "vertical"
  },
  "left": {
    "id": "fa4d5738c6bb2ba8",
    "type": "split",
    "children": [
      {
        "id": "a1d70964e275e53d",
        "type": "tabs",
        "children": [
          {
            "id": "b1f8eea1007e62c1",
            "type": "leaf",
            "state": {
              "type": "file-explorer",
              "state": {
                "sortOrder": "byModifiedTimeReverse"
              }
            }
          },
          {
            "id": "a05f6e181e6833e2",
            "type": "leaf",
            "state": {
              "type": "search",
              "state": {
                "query": "",
                "matchingCase": false,
                "explainSearch": false,
                "collapseAll": false,
                "extraContext": false,
                "sortOrder": "alphabetical"
              }
            }
          },
          {
            "id": "0c0c10599cc2050c",
            "type": "leaf",
            "state": {
              "type": "starred",
              "state": {}
            }
          }
        ]
      }
    ],
    "direction": "horizontal",
    "width": 315
  },
  "right": {
    "id": "c7f84e22265f9f0f",
    "type": "split",
    "children": [
      {
        "id": "a8df10ff80719fef",
        "type": "tabs",
        "children": [
          {
            "id": "7b80fcbfc8591b42",
            "type": "leaf",
            "state": {
              "type": "backlink",
              "state": {
                "file": "Untitled 1.md",
                "collapseAll": false,
                "extraContext": false,
                "sortOrder": "alphabetical",
                "showSearch": false,
                "searchQuery": "",
                "backlinkCollapsed": true,
                "unlinkedCollapsed": true
              }
            }
          },
          {
            "id": "e207e6549e464dbb",
            "type": "leaf",
            "state": {
              "type": "outline",
              "state": {
                "file": "Untitled 1.md"
              }
            }
          },
          {
            "id": "d18b2825c0806708",
            "type": "leaf",
            "state": {
              "type": "outgoing-link",
              "state": {
                "file": "Untitled 1.md",
                "linksCollapsed": false,
                "unlinkedCollapsed": true
              }
            }
          },
          {
            "id": "d39f54806fffa67b",
            "type": "leaf",
            "state": {
              "type": "graph-analysis",
              "state": {}
            }
          }
        ]
      }
    ],
    "direction": "horizontal",
    "width": 300,
    "collapsed": true
  },
  "left-ribbon": {
    "hiddenItems": {
      "switcher:Abrir quick switcher": false,
      "graph:Abrir vista de gráfico": false,
      "canvas:Create new canvas": false,
      "daily-notes:Abrir la nota de hoy": false,
      "templates:Insertar plantilla": false,
      "command-palette:Abrir paleta de comandos": false,
      "markdown-importer:Abrir el importador de Markdown": false,
      "random-note:Abrir nota al azar": false,
      "obsidian-full-calendar:Open Full Calendar": false
    }
  },
  "active": "9feaaa701d1f0a9f",
  "lastOpenFiles": [
    "2022-09-29.md",
    "Untitled 1.md",
    "2022/Bolillos parlantes 2022.md",
    "Personal/Evolución font.md",
    "2022/Preguntas final de 2022.md",
    "2022/Cine 2022.md",
    "2022/Calendario 2022.md",
    "2022/2022.md",
    "Notas diarias/2021-10-28 Odio Joker.md",
    "Notas diarias/2021-11-12 - Ensayo 2021.md"
  ]
}